googledata/__init__.py
googledata/user_agents.py
googledata-3.8.6.dist-info/METADATA
googledata-3.8.6.dist-info/WHEEL
googledata-3.8.6.dist-info/top_level.txt
googledata-3.8.6.dist-info/RECORD
