Metadata-Version: 2.1
Name: googledata
Version: 3.8.6
Summary: Codern Team Library from api free O - > api-free.ir
Home-page: https://github.com/Mahditerorist/search
Author: Mahdi Ahmadi
Author-email: mahdiahmadi.1208@gmail.com
Classifier: Programming Language :: Python :: 3
Classifier: License :: OSI Approved :: MIT License
Classifier: Operating System :: OS Independent
Requires-Python: >=3.6
Requires-Dist: requests
Requires-Dist: urllib3
